tqix/__init__.py
tqix/about.py
tqix/backend.py
tqix/hinfo.py
tqix/qmeas.py
tqix/qmetro.py
tqix/qobj.py
tqix/qoper.py
tqix/qstate.py
tqix/qtool.py
tqix/quasi_prob.py
tqix/utility.py
tqix/version.py
tqix/visualize.py
tqix/dsm/__init__.py
tqix/dsm/dsmProb.py
tqix/dsm/dsmProb_Conf_1.py
tqix/dsm/dsmProb_Conf_2.py
tqix/dsm/dsmStrong.py
tqix/dsm/dsmWeak.py
tqix/dsm/execute.py
tqix/dsm/util.py
tqix/pis/__init__.py
tqix/pis/circuit.py
tqix/pis/gates.py
tqix/pis/noise.py
tqix/pis/optimizers.py
tqix/pis/spin_operators.py
tqix/pis/squeeze_param.py
tqix/pis/util.py
tqix/povm/__init__.py
tqix/povm/mub.py
tqix/povm/pauli.py
tqix/povm/povm.py
tqix/povm/sic.py
tqix/povm/stoke.py
tqix/vqa/__init__.py
tqix/vqa/bounds.py
tqix/vqa/circuits.py
tqix/vqa/constants.py
tqix/vqa/entanglement.py
tqix/vqa/fitting.py
tqix/vqa/kraus.py
tqix/vqa/plateau.py
tqix/vqa/vqent.py
tqix/vqa/vqm.py
tqix-4.1.dist-info/LICENSE
tqix-4.1.dist-info/METADATA
tqix-4.1.dist-info/WHEEL
tqix-4.1.dist-info/top_level.txt
tqix-4.1.dist-info/RECORD
