Metadata-Version: 2.1
Name: tqix
Version: 4.1
Summary: A Toolbox for Quantum in X
Home-page: https://vqisinfo.wixsite.com/tqix
Author: Binho Le
Author-email: Binho Le <binho@fris.tohoku.ac.jp>
License: GNU
Requires-Python: >=3.6
License-File: LICENSE
